LICENSE.txt
MANIFEST.in
README.rst
VERSION
setup.py
seleniumdirector/__init__.py
seleniumdirector/exceptions.py
seleniumdirector/timemachine.js
seleniumdirector/webdirector.py
seleniumdirector/webelement.py
seleniumdirector.egg-info/PKG-INFO
seleniumdirector.egg-info/SOURCES.txt
seleniumdirector.egg-info/dependency_links.txt
seleniumdirector.egg-info/not-zip-safe
seleniumdirector.egg-info/requires.txt
seleniumdirector.egg-info/top_level.txt